<Properties StartupConfiguration="{4C0E9766-CDB9-466E-914F-C815C2C6F49D}|Default">
  <MonoDevelop.Ide.DebuggingService.Breakpoints>
    <BreakpointStore />
  </MonoDevelop.Ide.DebuggingService.Breakpoints>
  <MonoDevelop.Ide.Workbench ActiveDocument="Soccer_App/Soccer_App/View/MyFlyoutPage.xaml.cs">
    <Files>
      <File FileName="Soccer_App/Soccer_App/View/MyFlyoutPage.xaml" Line="13" Column="37" />
      <File FileName="Soccer_App/Soccer_App/View/MyFlyoutPage.xaml.cs" Line="33" Column="38" />
      <File FileName="Soccer_App/Soccer_App/Model/FlyoutItemPage_Model.cs" Line="15" Column="48" />
      <File FileName="Soccer_App/Soccer_App/ViewModel/VM_LeaguesList.cs" Line="92" Column="1" />
      <File FileName="Soccer_App/Soccer_App/View/LeaguesPage.xaml" Line="1" Column="1" />
      <File FileName="Soccer_App/Soccer_App/View/LeaguesPage.xaml.cs" Line="12" Column="13" />
      <File FileName="Soccer_App/Soccer_App.iOS/Main.cs" Line="17" Column="1" />
    </Files>
    <Pads>
      <Pad Id="ProjectPad">
        <State name="__root__">
          <Node name="Soccer_App" expanded="True">
            <Node name="Soccer_App" expanded="True">
              <Node name="Model" expanded="True" />
              <Node name="Service" expanded="True" />
              <Node name="View" expanded="True">
                <Node name="FlyoutMenuPage.xaml" expanded="True" />
                <Node name="HomePage.xaml" expanded="True" />
                <Node name="LeaguesPage.xaml" expanded="True" />
                <Node name="LivePage.xaml" expanded="True" />
                <Node name="MyFlyoutPage.xaml" expanded="True" />
                <Node name="SettingsPage.xaml" expanded="True" />
              </Node>
              <Node name="ViewModel" expanded="True" />
              <Node name="App.xaml" expanded="True" />
            </Node>
            <Node name="Soccer_App.iOS" expanded="True">
              <Node name="References" expanded="True" />
              <Node name="Resources" expanded="True" />
            </Node>
          </Node>
        </State>
      </Pad>
      <Pad Id="MonoDevelop.Debugger.WatchPad">
        <State>
          <Value>leagues</Value>
        </State>
      </Pad>
    </Pads>
  </MonoDevelop.Ide.Workbench>
  <MultiItemStartupConfigurations />
  <MonoDevelop.Ide.Workspace ActiveConfiguration="Debug|iPhoneSimulator" />
  <Xamarin.Addins.Core.Project ActiveDebugTarget="Android.SelectDevice" />
  <MonoDevelop.Ide.ItemProperties.Soccer__App.iOS PreferredExecutionTarget="MonoDevelop.IPhone.IPhoneSimulatorTarget.8FC422F7-01CB-48C3-A01A-0B9055E1EF7A" />
  <MonoDevelop.Ide.DebuggingService.PinnedWatches />
  <MonoDevelop.Ide.ItemProperties.Soccer__App.Android PreferredExecutionTarget="Android.SelectDevice" />
</Properties>